Metadata-Version: 2.1
Name: dl_multi_class
Version: 0.1.7
Summary: A sample package to create a sample multi class classification model
Author: Sastry K V S R
Author-email: pllsudha@gmail.com
Classifier: Programming Language :: Python :: 3
Classifier: License :: OSI Approved :: MIT License
Classifier: Operating System :: OS Independent
Requires-Python: >=3.6
Requires-Dist: tensorflow
